hyputils/__init__.py
hyputils/handlers.py
hyputils/hypothesis.py
hyputils/subscribe.py
hyputils/utils.py
hyputils/wstest.py
hyputils/memex/__init__.py
hyputils/memex/_compat.py
hyputils/memex/pubid.py
hyputils/memex/security.py
hyputils/memex/settings.py
hyputils/memex/db/__init__.py
hyputils/memex/db/mixins.py
hyputils/memex/db/types.py
hyputils/memex/models/__init__.py
hyputils/memex/models/annotation.py
hyputils/memex/models/document.py
hyputils/memex/models/group.py
hyputils/memex/models/organization.py
hyputils/memex/models/user.py
hyputils/memex/models/user_identity.py
hyputils/memex/schemas/__init__.py
hyputils/memex/schemas/annotation.py
hyputils/memex/schemas/base.py
hyputils/memex/util/__init__.py
hyputils/memex/util/document_claims.py
hyputils/memex/util/group.py
hyputils/memex/util/markdown.py
hyputils/memex/util/uri.py
hyputils/memex/util/user.py
hyputils-0.0.10.dist-info/LICENSE
hyputils-0.0.10.dist-info/METADATA
hyputils-0.0.10.dist-info/WHEEL
hyputils-0.0.10.dist-info/top_level.txt
hyputils-0.0.10.dist-info/RECORD
