Metadata-Version: 2.1
Name: hyputils
Version: 0.0.10
Summary: Python utilities for the Hypothes.is REST api and websocket interface
Home-page: https://github.com/tgbugs/hyputils
Author: Tom Gillespie
Author-email: tgbugs@gmail.com
License: MIT
Keywords: hypothesis hypothes.is web annotation
Classifier: Development Status :: 4 - Beta
Classifier: License :: OSI Approved :: MIT License
Classifier: Programming Language :: Python :: 3.7
Classifier: Programming Language :: Python :: 3.8
Classifier: Programming Language :: Python :: 3.9
Classifier: Programming Language :: Python :: 3.10
Classifier: Programming Language :: Python :: 3.11
Classifier: Programming Language :: Python :: 3.12
Classifier: Programming Language :: Python :: 3.13
Classifier: Programming Language :: Python :: Implementation :: CPython
Classifier: Programming Language :: Python :: Implementation :: PyPy
Classifier: Operating System :: POSIX :: Linux
Classifier: Operating System :: MacOS :: MacOS X
Classifier: Operating System :: Microsoft :: Windows
Requires-Python: >=3.7
License-File: LICENSE
Requires-Dist: appdirs
Requires-Dist: certifi
Requires-Dist: psutil
Requires-Dist: requests
Requires-Dist: websockets
Provides-Extra: dev
Requires-Dist: pytest-cov; extra == "dev"
Requires-Dist: wheel; extra == "dev"
Provides-Extra: memex
Requires-Dist: python-dateutil; extra == "memex"
Requires-Dist: bleach; extra == "memex"
Requires-Dist: jsonschema; extra == "memex"
Requires-Dist: mistune; extra == "memex"
Requires-Dist: psycopg2; implementation_name != "pypy" and extra == "memex"
Requires-Dist: psycopg2cffi; implementation_name == "pypy" and extra == "memex"
Requires-Dist: python-slugify; extra == "memex"
Requires-Dist: sqlalchemy; extra == "memex"
Requires-Dist: webob; extra == "memex"
Provides-Extra: test
Requires-Dist: factory-boy; extra == "test"
Requires-Dist: pytest; extra == "test"
Requires-Dist: bleach; extra == "test"
Requires-Dist: jsonschema; extra == "test"
Requires-Dist: mistune; extra == "test"
Requires-Dist: psycopg2; implementation_name != "pypy" and extra == "test"
Requires-Dist: psycopg2cffi; implementation_name == "pypy" and extra == "test"
Requires-Dist: python-slugify; extra == "test"
Requires-Dist: sqlalchemy; extra == "test"
Requires-Dist: webob; extra == "test"
Provides-Extra: zdesk
Requires-Dist: pyyaml; extra == "zdesk"
Requires-Dist: zdesk; extra == "zdesk"
